LICENSE
MANIFEST.in
README.rst
setup.py
iface/__init__.py
iface/checks.py
iface/decorators.py
iface/ibc.py
iface/test_checks.py
iface/test_ibc.py
iface.egg-info/PKG-INFO
iface.egg-info/SOURCES.txt
iface.egg-info/dependency_links.txt
iface.egg-info/entry_points.txt
iface.egg-info/requires.txt
iface.egg-info/top_level.txt