Metadata-Version: 1.0
Name: iface
Version: 0.1.2
Summary: Implementable interfaces for Python.
Home-page: https://github.com/kevinconway/iface
Author: Kevin Conway
Author-email: kevinjacobconway@gmail.com
License: Apache 2.0
Platform: UNKNOWN
